[
   {
      "name":"世界篇1章",
      "condition":"取得日本篇第一章所有金寶",
      "grade":0
   },
   {
      "name":"世界篇2章",
      "condition":"取得日本篇第二章所有金寶",
      "grade":1
   },
   {
      "name":"世界篇3章",
      "condition":"取得日本篇第三章所有金寶",
      "grade":2
   },
   {
      "name":"奪還世界I",
      "condition":"日本篇第一章不死生物來襲全通",
      "grade":0
   },
   {
      "name":"奪還世界II",
      "condition":"日本篇第二章不死生物來襲全通",
      "grade":1
   },
   {
      "name":"奪還世界III",
      "condition":"日本篇第三章不死生物來襲全通",
      "grade":2
   },
   {
      "name":"未來篇1章",
      "condition":"取得未來篇第一章所有金寶",
      "grade":0
   },
   {
      "name":"未來篇2章",
      "condition":"取得未來篇第二章所有金寶",
      "grade":1
   },
   {
      "name":"未來篇3章",
      "condition":"取得未來篇第三章所有金寶",
      "grade":2
   },
   {
      "name":"奪還未來I",
      "condition":"未來篇第一章不死生物來襲全通",
      "grade":0
   },
   {
      "name":"奪還未來II",
      "condition":"未來篇第二章不死生物來襲全通",
      "grade":1
   },
   {
      "name":"宇宙篇1章",
      "condition":"取得宇宙篇第一章所有金寶",
      "grade":0
   },
   {
      "name":"宇宙篇2章",
      "condition":"取得宇宙篇第二章所有金寶",
      "grade":1
   },
   {
      "name":"宇宙篇3章",
      "condition":"取得宇宙篇第三章所有金寶",
      "grade":2
   },
   {
      "name":"侵略者擊破",
      "condition":"打倒在宇宙篇第三章出現的迷之生命體",
      "grade":3
   },
   {
      "name":"傳說的貓咪I",
      "condition":"傳奇關卡★1難度全通",
      "grade":0
   },
   {
      "name":"傳說的貓咪II",
      "condition":"傳奇關卡★2難度全通",
      "grade":1
   },
   {
      "name":"傳說的貓咪III",
      "condition":"傳奇關卡★3難度全通",
      "grade":2
   },
   {
      "name":"赤色旋風",
      "condition":"通關[紅色突變]\n",
      "grade":1
   },
   {
      "name":"暗黑旋風",
      "condition":"通關[黑暗天堂]\n",
      "grade":1
   },
   {
      "name":"白金旋風",
      "condition":"通關[國士無雙]\n",
      "grade":1
   },
   {
      "name":"天使旋風",
      "condition":"通關[天譴]\n",
      "grade":1
   },
   {
      "name":"鋼鐵旋風",
      "condition":"通關[鐵子的部屋]",
      "grade":1
   },
   {
      "name":"宇宙旋風",
      "condition":"通關[絕望異次元]",
      "grade":1
   },
   {
      "name":"猛烈旋風",
      "condition":"通關[緊急暴風警報]",
      "grade":1
   },
   {
      "name":"D旋風",
      "condition":"通關[滾死樂團]",
      "grade":1
   },
   {
      "name":"異次元旋風",
      "condition":"通關[絕望新次元]",
      "grade":1
   },
   {
      "name":"古代旋風",
      "condition":"通關[零號颱風]",
      "grade":1
   },
   {
      "name":"天使降臨",
      "condition":"通關[斷罪天使海蝶降臨]",
      "grade":2
   },
   {
      "name":"地獄門",
      "condition":"通關[地獄門]",
      "grade":2
   },
   {
      "name":"女帝飛來",
      "condition":"通關[女帝飛來]",
      "grade":2
   },
   {
      "name":"亡者降臨",
      "condition":"通關[亡者肥普降臨]",
      "grade":2
   },
   {
      "name":"伯爵降臨",
      "condition":"通關[吉娃娃伯爵降臨]",
      "grade":2
   },
   {
      "name":"少女做夢吧",
      "condition":"通關[春宵苦短, 少女做夢吧！]",
      "grade":2
   },
   {
      "name":"河豚星球",
      "condition":"通關[藍色衝擊]",
      "grade":2
   },
   {
      "name":"討伐狂亂",
      "condition":"狂亂貓關卡全通",
      "grade":2
   },
   {
      "name":"討伐大狂亂",
      "condition":"大狂亂貓關卡全通",
      "grade":2
   },
   {
      "name":"討伐小小貓",
      "condition":"小小貓關卡全通",
      "grade":2
   },
   {
      "name":"新年",
      "condition":"通關1月月份關[新年快樂？]",
      "grade":0
   },
   {
      "name":"節分",
      "condition":"通關2月月份關[被召喚的福！]",
      "grade":0
   },
   {
      "name":"女兒節",
      "condition":"通關3月月份關[人偶架上的戰士們]",
      "grade":0
   },
   {
      "name":"青春",
      "condition":"通關4月月份關[春天來了！高校教師]",
      "grade":0
   },
   {
      "name":"戀愛至上",
      "condition":"通關5月月份關[相思病戀歌]",
      "grade":0
   },
   {
      "name":"結婚",
      "condition":"通關6月月份關[禁斷之妻]",
      "grade":0
   },
   {
      "name":"真夏",
      "condition":"通關7月月份關[因為夏天喵！]",
      "grade":0
   },
   {
      "name":"歸鄉",
      "condition":"通關8月月份關[返鄉熱潮！]",
      "grade":0
   },
   {
      "name":"敬老",
      "condition":"通關9月月份關[在鎮上看到的超強老人]",
      "grade":0
   },
   {
      "name":"運動會",
      "condition":"通關10月月份關[秋天運動會！]",
      "grade":0
   },
   {
      "name":"勞動",
      "condition":"通關11月月份關[勞動感謝特別活動！]",
      "grade":0
   },
   {
      "name":"平安夜",
      "condition":"通關12月月份關[聖誕節居然來了！]",
      "grade":0
   },
   {
      "name":"塔30階",
      "condition":"通關[風雲貓咪塔 - 30樓]",
      "grade":2
   },
   {
      "name":"塔40階",
      "condition":"通關[風雲貓咪塔 - 40樓]",
      "grade":3
   },
   {
      "name":"LEVEL FINAL",
      "condition":"通關[傳奇尋寶記]",
      "grade":3
   },
   {
      "name":"富豪I",
      "condition":"戰鬥中生產貓咪金額累積突破100萬",
      "grade":0
   },
   {
      "name":"富豪II",
      "condition":"戰鬥中生產貓咪金額累積突破500萬",
      "grade":0
   },
   {
      "name":"大富豪I",
      "condition":"戰鬥中生產貓咪金額累積突破1000萬",
      "grade":0
   },
   {
      "name":"大富豪II",
      "condition":"戰鬥中生產貓咪金額累積突破5000萬",
      "grade":0
   },
   {
      "name":"超富豪I",
      "condition":"戰鬥中生產貓咪金額累積突破1億",
      "grade":0
   },
   {
      "name":"超富豪II",
      "condition":"戰鬥中生產貓咪金額累積突破2億",
      "grade":0
   },
   {
      "name":"冒險家I",
      "condition":"加碼多多探險時間累積突破1000小時",
      "grade":0
   },
   {
      "name":"發明家I",
      "condition":"開發5種貓砲主砲",
      "grade":1
   },
   {
      "name":"等級提高I",
      "condition":"等級排行(Rank)到達1000",
      "grade":1
   },
   {
      "name":"精英夥伴I",
      "condition":"加碼多多探險隊發現1名精英隊員(金帽)",
      "grade":1
   },
   {
      "name":"少女",
      "condition":"取得“狼與少女”\n(傳奇關卡18-6[越獄隧道 - 大逃亡]掉落)",
      "grade":2
   },
   {
      "name":"貓彈",
      "condition":"取得“小戰士貓彈”\n(傳奇關卡23-6[終焉宣告之夜 - 紅狐之聖者]掉落)",
      "grade":2
   },
   {
      "name":"咪娜",
      "condition":"取得“貓紅帽咪娜”\n(傳奇關卡28-6[脆弱性和弱酸性 - 剛學會去愛]掉落)",
      "grade":2
   },
   {
      "name":"宮木武藏",
      "condition":"取得“宮木武藏”\n(傳奇關卡37-6[豪來塢帝國 - 大膽換囚影城]掉落)",
      "grade":2
   },
   {
      "name":"貓騎士",
      "condition":"取得“噴噴貓騎士”\n(傳奇關卡49-1[古代研究所 - 太古之力]掉落)",
      "grade":2
   },
   {
      "name":"喵丸",
      "condition":"取得“土偶喵丸”\n(真傳奇關卡12-6[打從魂魄的歸化 - 原始旅居魂]掉落)",
      "grade":2
   }
]
